ProsperCommon-1.5.1.dist-info/METADATA
ProsperCommon-1.5.1.dist-info/RECORD
ProsperCommon-1.5.1.dist-info/WHEEL
ProsperCommon-1.5.1.dist-info/entry_points.txt
ProsperCommon-1.5.1.dist-info/top_level.txt
prosper/common/__init__.py
prosper/common/_version.py
prosper/common/common_config.cfg
prosper/common/exceptions.py
prosper/common/flask_utils.py
prosper/common/prosper_cli.py
prosper/common/prosper_config.py
prosper/common/prosper_logging.py
prosper/common/prosper_version.py
prosper/common/version.txt
