Metadata-Version: 2.1
Name: ProsperCommon
Version: 1.5.1
Summary: Common Utilities for EVEProsper Projects
Home-page: https://github.com/EVEprosper/ProsperCommon
Author: John Purcell
Author-email: prospermarketshow@gmail.com
License: MIT
Keywords: prosper eve-online webhooks logging configuration-management
Platform: UNKNOWN
Classifier: Programming Language :: Python :: 3.5
Classifier: Programming Language :: Python :: 3.6
Provides-Extra: dev
Provides-Extra: test
Requires-Dist: anyconfig
Requires-Dist: anytemplate
Requires-Dist: jinja2
Requires-Dist: plumbum
Requires-Dist: requests
Requires-Dist: semantic-version
Provides-Extra: dev
Requires-Dist: sphinx; extra == 'dev'
Requires-Dist: sphinxcontrib-napoleon; extra == 'dev'
Provides-Extra: test
Requires-Dist: plumbum; extra == 'test'
Requires-Dist: docker; extra == 'test'
